[
  {
    "full_name": "Iamzaryab/Flutter-Movie-App-with-Clean-Architecture-and-RiverPod-State-Management",
    "stargazers_count": 72,
    "open_issues_count": 1,
    "forks_count": 16
  },
  {
    "full_name": "aloisdeniel/asgard_shop",
    "stargazers_count": 147,
    "open_issues_count": 2,
    "forks_count": 39
  },
  {
    "full_name": "Unity-Technologies/megacity-metro",
    "stargazers_count": 653,
    "open_issues_count": 0,
    "forks_count": 168
  },
  {
    "full_name": "panagiop/node.js-clean-architecture",
    "stargazers_count": 967,
    "open_issues_count": 2,
    "forks_count": 184
  },
  {
    "full_name": "gayanvoice/top-github-users",
    "stargazers_count": 3983,
    "open_issues_count": 157,
    "forks_count": 582
  },
  {
    "full_name": "Fabrice-Fabio/riverpood-clean-archi-flutter",
    "stargazers_count": 43,
    "open_issues_count": 0,
    "forks_count": 10
  },
  {
    "full_name": "gskinnerTeam/flutter-wonderous-app",
    "stargazers_count": 4086,
    "open_issues_count": 31,
    "forks_count": 957
  },
  {
    "full_name": "gibbok/typescript-book",
    "stargazers_count": 8493,
    "open_issues_count": 1,
    "forks_count": 526
  },
  {
    "full_name": "mbeaudru/modern-js-cheatsheet",
    "stargazers_count": 25436,
    "open_issues_count": 9,
    "forks_count": 3175
  },
  {
    "full_name": "popekabu/pay_with_paystack",
    "stargazers_count": 10,
    "open_issues_count": 2,
    "forks_count": 26
  },
  {
    "full_name": "ravi84184/flutter_hr_management_design",
    "stargazers_count": 108,
    "open_issues_count": 2,
    "forks_count": 49
  },
  {
    "full_name": "abuanwar072/Flutter-Responsive-Admin-Panel-or-Dashboard",
    "stargazers_count": 6773,
    "open_issues_count": 32,
    "forks_count": 1923
  },
  {
    "full_name": "mesrenyamedogbe/made-in-ghana",
    "stargazers_count": 83,
    "open_issues_count": 0,
    "forks_count": 33
  },
  {
    "full_name": "Frave07/Flutter-Delivery-App",
    "stargazers_count": 280,
    "open_issues_count": 4,
    "forks_count": 154
  },
  {
    "full_name": "Frave07/Flutter-Social-Media-App",
    "stargazers_count": 58,
    "open_issues_count": 2,
    "forks_count": 25
  },
  {
    "full_name": "yfosp/start-here",
    "stargazers_count": 236,
    "open_issues_count": 1,
    "forks_count": 289
  },
  {
    "full_name": "flutter/flutter",
    "stargazers_count": 167416,
    "open_issues_count": 13273,
    "forks_count": 27764
  },
  {
    "full_name": "VeriorPies/ParrelSync",
    "stargazers_count": 4863,
    "open_issues_count": 37,
    "forks_count": 332
  },
  {
    "full_name": "total-typescript/beginners-typescript-tutorial",
    "stargazers_count": 7809,
    "open_issues_count": 12,
    "forks_count": 1029
  },
  {
    "full_name": "danfortsystems/recruitment-and-onboarding",
    "stargazers_count": 1,
    "open_issues_count": 0,
    "forks_count": 0
  },
  {
    "full_name": "Kirsten-Nancy/Quiz-App",
    "stargazers_count": 4,
    "open_issues_count": 0,
    "forks_count": 0
  },
  {
    "full_name": "lohanidamodar/flutter_opentrivia",
    "stargazers_count": 284,
    "open_issues_count": 1,
    "forks_count": 108
  },
  {
    "full_name": "markmead/hyperui",
    "stargazers_count": 10412,
    "open_issues_count": 0,
    "forks_count": 411
  },
  {
    "full_name": "Chalarangelo/30-seconds-of-code",
    "stargazers_count": 122202,
    "open_issues_count": 0,
    "forks_count": 12053
  },
  {
    "full_name": "alan2207/bulletproof-react",
    "stargazers_count": 29069,
    "open_issues_count": 36,
    "forks_count": 2639
  },
  {
    "full_name": "Developer-Y/cs-video-courses",
    "stargazers_count": 67604,
    "open_issues_count": 5,
    "forks_count": 9159
  },
  {
    "full_name": "JohannesMilke/firebase_chat_example",
    "stargazers_count": 54,
    "open_issues_count": 2,
    "forks_count": 65
  },
  {
    "full_name": "itsmefarhan/react-firebase-chat",
    "stargazers_count": 46,
    "open_issues_count": 2,
    "forks_count": 24
  },
  {
    "full_name": "aswara/Admin-eCommerce-ReactJS",
    "stargazers_count": 77,
    "open_issues_count": 5,
    "forks_count": 35
  },
  {
    "full_name": "Adrinlol/landy-react-template",
    "stargazers_count": 1349,
    "open_issues_count": 5,
    "forks_count": 678
  }
]